{
  "version": 3,
  "schemaVersion": "1.0",
  "intentRules": {
    "personNamePatterns": {
      "beforeAction": [
        "([\\u4e00-\\u9fa5]{2,4})\\s*(负责|管|监管|保管|执行)"
      ],
      "beforeResign": [
        "([\\u4e00-\\u9fa5]{2,4})\\s*离职"
      ],
      "leadingName": [
        "^([\\u4e00-\\u9fa5]{2,3})(?=[，,。；;：:？?！!、\\s]|离职|负责|管|是|在|的|有)"
      ],
      "pronounBlocklist": [
        "她",
        "他",
        "它",
        "其",
        "这",
        "那",
        "谁",
        "哪",
        "啥",
        "什"
      ],
      "honorificSuffixes": [
        "先生",
        "女士",
        "小姐",
        "老师",
        "经理",
        "总监",
        "总裁",
        "董事",
        "总",
        "工"
      ]
    },
    "strategyInferenceConditions": []
  },
  "certificateRetrieval": {
    "personQueryConfigId": "person_stewardship",
    "companyQueryConfigId": "certificate_by_company",
    "graphInstanceSource": "neo4j-certificate-instance",
    "forbidUnscopedGlobalScan": true,
    "activeCompanyOperatingStatusCodes": [
      "1",
      "2"
    ],
    "activeCertificateStatusValues": [
      "0",
      "有效",
      "生效中"
    ]
  },
  "dataSources": {
    "structuredQueries": []
  },
  "correctionRules": [
    {
      "id": "company_correction",
      "description": "公司纠偏 - 用户纠正公司名称时过滤到精确匹配",
      "prefixPatterns": [
        "^不对",
        "^不是",
        "^错了",
        "^错啦",
        "^说错了",
        "^你搞错了",
        "^搞错了",
        "^纠正一下",
        "^更正",
        "^应该是",
        "^其实是",
        "^正确是",
        "^应当是"
      ],
      "entityPattern": "(?:总部|母公司|总公司|主体)(?:是|为|：|:)?\\s*([^，,。；;？?！!\\n]+(?:有限公司|有限责任公司|股份有限公司|分公司|公司))",
      "entityType": "company",
      "suffixes": [
        "有限公司",
        "有限责任公司",
        "股份有限公司",
        "分公司",
        "公司"
      ],
      "relatedKeywords": [
        "分公司",
        "子公司",
        "下属",
        "有哪些公司",
        "哪些主体",
        "分支机构"
      ]
    }
  ],
  "conversationScope": {
    "breakContextPhrases": [
      "无关上文",
      "与上文无关",
      "和上文无关",
      "不关联上文",
      "不参考上文",
      "忽略上文",
      "忽略之前",
      "忽略刚才",
      "忽略之前的问题",
      "不要结合上文",
      "不看上文",
      "脱离上文",
      "独立问题",
      "独立提问",
      "新问题",
      "新话题",
      "重新开始",
      "换个话题",
      "另起一题"
    ],
    "globalListMarkers": [
      "所有",
      "全部",
      "凡",
      "列举",
      "列出",
      "清单"
    ],
    "globalListContextKeywords": [
      "证照",
      "许可证",
      "执照",
      "备案",
      "证书",
      "证",
      "主体"
    ],
    "catalogQuestionMarkers": [
      "哪些种类",
      "什么种类",
      "包含哪些种类",
      "包含哪些类型",
      "有哪些类型",
      "什么类型",
      "有哪些种类",
      "包含哪些状态",
      "有哪些状态"
    ],
    "continuationMarkers": [
      "它",
      "其",
      "该",
      "这家",
      "那家",
      "上面",
      "刚才",
      "之前",
      "接着",
      "继续",
      "再",
      "还有",
      "同样",
      "那",
      "然后",
      "另外",
      "顺便",
      "对吧",
      "是不是",
      "对吗",
      "呢",
      "吗",
      "嘛",
      "啥",
      "多少",
      "几个",
      "具体",
      "详细",
      "分别",
      "哪些",
      "什么",
      "谁",
      "不对",
      "错了"
    ],
    "continuationExcludePatterns": [
      "不是存续",
      "不是在业",
      "非存续",
      "非在业",
      "忽略之前",
      "忽略刚才",
      "所有",
      "全部"
    ],
    "continuationMaxLength": 80,
    "operatingStatus": {
      "activeMarkers": [
        "存续",
        "在业",
        "开业",
        "正常"
      ],
      "inactiveMarkers": [
        "吊销",
        "注销",
        "失效",
        "停业",
        "撤销",
        "清算",
        "迁出",
        "异常"
      ],
      "negationPrefixes": [
        "非",
        "不是",
        "并非",
        "不属于"
      ],
      "inactivePhrases": [
        "不是存续",
        "不是在业",
        "非存续",
        "非在业",
        "主体不是存续",
        "主体不是在业"
      ],
      "certificateContextKeywords": [
        "证照",
        "许可证",
        "执照",
        "备案",
        "证书",
        "证",
        "资质"
      ]
    }
  },
  "intentRouting": {
    "structuredListStrategies": [
      "structured_list",
      "graph_relational"
    ],
    "defaultIntentByStrategy": {
      "structured_list": "hybrid"
    },
    "followUpReferenceMarkers": [
      "这些",
      "上面",
      "刚才",
      "存续",
      "主体",
      "它们",
      "那些",
      "这几",
      "那几"
    ],
    "filterRulePrefixes": [
      "只要",
      "凡是",
      "如果",
      "对于",
      "关于",
      "按照",
      "按",
      "不是存续",
      "不是在业"
    ],
    "compiledDocumentKeywords": [
      "证照",
      "许可证",
      "备案",
      "印章",
      "公章"
    ],
    "strategySlotRequirements": [
      {
        "retrievalStrategy": "graph_relational",
        "requiresPerson": true,
        "requiresCompany": false,
        "requiresRoleFocus": true
      },
      {
        "retrievalStrategy": "structured_list",
        "requiresPerson": true,
        "requiresCompany": false,
        "requiresRoleFocus": false
      },
      {
        "retrievalStrategy": "structured_list",
        "requiresPerson": false,
        "requiresCompany": true,
        "requiresRoleFocus": false
      },
      {
        "retrievalStrategy": "instance_fact",
        "requiresPerson": false,
        "requiresCompany": true,
        "requiresRoleFocus": false
      },
      {
        "retrievalStrategy": "graph_relational",
        "requiresPerson": false,
        "requiresCompany": false,
        "requiresRoleFocus": false
      }
    ]
  },
  "answerGate": {
    "requiredEvidenceByNeed": [
      {
        "facet": "certificate",
        "granularity": "instance",
        "requiresPerson": true,
        "schemaIds": [
          "person_certificate_v1"
        ]
      },
      {
        "facet": "certificate",
        "granularity": "instance",
        "requiresPerson": false,
        "schemaIds": [
          "person_certificate_v1"
        ]
      }
    ]
  },
  "filterFieldCoverageRules": [
    {
      "id": "establishment_date",
      "displayLabel": "成立日期",
      "questionAnyKeywords": [
        "成立时间",
        "成立日期",
        "设立日期"
      ],
      "filterIntentKeywords": [
        "有哪些",
        "超过",
        "以上",
        "以下",
        "之前",
        "之后",
        "年"
      ],
      "snippetMarkers": [
        "成立日期",
        "成立时间",
        "establishment_date",
        "establishedDate"
      ],
      "sourceColumns": [
        "establishment_date",
        "established_date",
        "setup_date"
      ]
    }
  ],
  "retrievalThresholds": {
    "sourceThresholds": [],
    "preferActiveLearning": {
      "maxLengthShort": 14,
      "minScoreStrongLearned": 2.5,
      "memoryLikeKeywords": [
        "总部",
        "总公司",
        "是啥",
        "是什么",
        "还记得",
        "记得"
      ]
    },
    "activeLearningMerge": {
      "explicitCompanyHintThreshold": 2.0,
      "implicitThreshold": 1.0,
      "prefixLimit": 4
    },
    "answerGate": {
      "minTopScore": 3.0,
      "minEvidenceCount": 1,
      "llmAssistConfidence": 0.7
    },
    "trim": {
      "default": 20,
      "bySource": {
        "neo4j-certificate-instance": 50,
        "mysql-structured-certificate": 50
      },
      "byStrategy": {
        "graph_relational": 30,
        "structured_list": 50
      }
    }
  },
  "outputContracts": {
    "default": "当证据为多条并列记录时，须列全证据中的条目，结论中的条数须与证据条数一致；仅使用证据片段里已出现的属性名与取值作答。",
    "list_query": "【输出契约 list_query】证据为多条记录时：须列全全部条目，可先给总数再列清单；结论条数与证据条数一致。",
    "structured_row": "【输出契约 structured_row】证据为结构化键值行时：按行逐条列出片段中的各属性；不得用证据未出现的维度作答；若用户追问「类型」且上下文为相关主题，仅列类型名称（可去重）。",
    "identity_resolution": "【输出契约 identity_resolution】当证据片段呈现同一实体的身份属性对照时，可据该片段回答不同称呼是否指同一实体；已有对照时勿称「证据未包含」。",
    "entity_correction": "【输出契约 entity_correction】用户在否定上一轮并给出正确主体/事实时：先简短确认纠偏（勿用「是的」附和错误前提）；仅回答用户本轮关心的维度；未明确要求时不要罗列关联主体；不得从分支状态推断主体状态。",
    "canonical_fact": "【输出契约 canonical_fact】证据来源为 canonical 时：可据片段中的属性直接作答；勿与结构化库字段矛盾；若仅有常识而无其它明细，说明「常识层已确认，详细字段需另查」。",
    "role_list": "【输出契约 role_list】证据为多条任职/角色记录时：须列全全部主体或角色归属，可先给总数再列清单；结论条数与证据条数一致。",
    "certificate_instance": "【输出契约 certificate_instance】证据为结构化键值行时：按行逐条列出片段中的各属性（如类型、所属组织、职责角色、状态等）；不得用证据未出现的维度作答；若用户追问「类型」且上下文为证照主题，仅列类型名称（可去重）。术语约束：证照类型是类别标签，证照是该企业在该类型下的一条实例记录；未见多条实例证据时，不要把同一企业同一类型拆成多本证照。",
    "certificate_instance_company": "【输出契约 certificate_instance_company】证据为公司证照记录时：须列全全部证照类型及状态；结论条数与证据条数一致。术语约束：默认按“企业+证照类型”对应一条证照实例汇总，除非证据明确显示同类型存在多条不同记录（如编号/有效期/状态不同）。",
    "profile_instance": "【输出契约 profile_instance】证据为公司概况时：按问句关心的维度回答；不得罗列无关属性。",
    "type_catalog": "【输出契约 type_catalog】证据为类型/枚举目录时：仅列类型名称（可去重），不展开实例明细。",
    "aggregate": "【输出契约 aggregate】证据为聚合统计时：给出统计结论并说明依据字段。"
  },
  "evidenceMergeRules": {
    "activeLearningRetention": "lexicon_above_threshold",
    "foreignCertificateDrop": true,
    "aliasRewriteDropsPrecheck": true,
    "queryTypeOffScopeDemote": false
  }
}
